StructPy/__init__.py
StructPy/node.py
StructPy/queue.py
StructPy/stack.py
StructPy/tree.py
PyStruct_williamstella-0.0.1.dist-info/LICENCE
PyStruct_williamstella-0.0.1.dist-info/METADATA
PyStruct_williamstella-0.0.1.dist-info/WHEEL
PyStruct_williamstella-0.0.1.dist-info/top_level.txt
PyStruct_williamstella-0.0.1.dist-info/RECORD
