Metadata-Version: 2.1
Name: PyStruct-williamstella
Version: 0.0.1
Summary: A small data-structures library in Python
Home-page: https://github.com/wastella/PyStruct
Author: William Stella
Author-email: william.a.stella@gmail.com
License: UNKNOWN
Platform: UNKNOWN
Classifier: Programming Language :: Python :: 3
Classifier: License :: OSI Approved :: MIT License
Classifier: Operating System :: OS Independent
Requires-Python: >=3.6
